Metadata-Version: 2.1
Name: csvplus
Version: 0.0.2
Summary: Create, Read, Update, Delete, and Move Rows in a CSV File
Home-page: https://github.com/DanielJDufour/csvplus
Download-URL: https://github.com/DanielJDufour/csvplus/tarball/download
Author: Daniel J. Dufour
Author-email: daniel.j.dufour@gmail.com
Keywords: create,crud,csv,delete,move,read,update
Classifier: Programming Language :: Python :: 3
Classifier: Operating System :: OS Independent
License-File: LICENSE
